{
  "customers": [
    {
      "fullName": "Lê Minh Cường",
      "phone": "0909123456",
      "email": "cuong@gmail.com",
      "course": "JavaScript cơ bản",
      "status": "contacted",
      "isFavorite": true,
      "note": "Đã đăng ký học cuối tuần",
      "id": "3"
    },
    {
      "fullName": "Anna Smith T",
      "phone": "0000000009",
      "email": "anna@gmail.com",
      "course": "java",
      "status": "new",
      "isFavorite": true,
      "note": "aâ",
      "id": "w7HSoXv"
    },
    {
      "fullName": "Anna Smith T",
      "phone": "0766938732",
      "email": "quangglee0000@gmail.com",
      "course": "tester",
      "status": "registered",
      "isFavorite": false,
      "note": "sssss",
      "id": "7rrwe7a"
    },
    {
      "fullName": "Nguyen Van A",
      "phone": "0766938732",
      "email": "quangglee0000@gmail.com",
      "course": "ssss",
      "status": "new",
      "favorite": true,
      "note": "sss",
      "id": "2LB01IM"
    },
    {
      "fullName": "Lê Minh Cường",
      "phone": "0909123456",
      "email": "cuong@gmail.com",
      "course": "JavaScript cơ bản",
      "status": "new",
      "isFavorite": false,
      "note": "",
      "id": "_eBPeCb"
    }
  ]
}